pygobgp/__init__.py
pygobgp/errors.py
pygobgp/gobgp_pb2.py
pygobgp/gobgp_pb2_grpc.py
pygobgp/pygobgp.py
pygobgp-0.1.2.dist-info/METADATA
pygobgp-0.1.2.dist-info/RECORD
pygobgp-0.1.2.dist-info/WHEEL
pygobgp-0.1.2.dist-info/top_level.txt
test/__init__.py
