Metadata-Version: 2.1
Name: pygobgp
Version: 0.1.2
Summary: Python library to interact GoBGP
Home-page: UNKNOWN
Author: Mehmet Oner Yalcin
Author-email: oneryalcin@gmail.com
License: Apache
Platform: Linux
Classifier: Development Status :: 2 - Pre-Alpha
Classifier: Intended Audience :: Telecommunications Industry
Classifier: License :: OSI Approved :: Apache Software License
Classifier: Natural Language :: English
Classifier: Programming Language :: Python :: 3.5
Classifier: Programming Language :: Python :: 3.6
Classifier: Programming Language :: Python :: 3.7
Requires-Dist: grpcio (==1.15.0)
Requires-Dist: grpcio-tools (==1.15.0)
Requires-Dist: googleapis-common-protos (==1.5.3)
